flowtool_githooks/__init__.py
flowtool_githooks/_version.py
flowtool_githooks/config.py
flowtool_githooks/discovering.py
flowtool_githooks/insert.py
flowtool_githooks/manager.py
flowtool_githooks/probe_hooks.py
flowtool_githooks/runner.py
flowtool_githooks/status.py
flowtool_githooks/managed_hooks/__init__.py
flowtool_githooks/managed_hooks/shellcommands.py
flowtool_githooks/managed_hooks/universal.py
flowtool_githooks/scripts/generic-hook-runner.sh
flowtool_githooks-0.7.46.dist-info/DESCRIPTION.rst
flowtool_githooks-0.7.46.dist-info/METADATA
flowtool_githooks-0.7.46.dist-info/RECORD
flowtool_githooks-0.7.46.dist-info/WHEEL
flowtool_githooks-0.7.46.dist-info/entry_points.txt
flowtool_githooks-0.7.46.dist-info/metadata.json
flowtool_githooks-0.7.46.dist-info/top_level.txt
tests/__init__.py
tests/conftest.py
tests/setup_command.py
tests/test_config.py
tests/test_probehooks.py
tests/test_runner.py
